hikari/__init__.py
hikari/dataframes/__init__.py
hikari/dataframes/base.py
hikari/dataframes/cif.py
hikari/dataframes/hkl.py
hikari/dataframes/lst.py
hikari/dataframes/res.py
hikari/dataframes/ubase.py
hikari/resources/Xray_atomic_form_factors.csv
hikari/resources/__init__.py
hikari/resources/characteristic_radiation.json
hikari/resources/cif_core_2.4.5.dic
hikari/resources/gnuplot_angular_heatmap_template.gnu
hikari/resources/hkl.msd
hikari/resources/hkl_formats_aliases.json
hikari/resources/hkl_formats_defined.json
hikari/resources/point_groups.json
hikari/resources/point_groups.wsv
hikari/resources/space_groups.json
hikari/resources/space_groups.wsv
hikari/scripts/__init__.py
hikari/scripts/angular_explorer.py
hikari/scripts/compare_adps.py
hikari/scripts/fcf.py
hikari/scripts/hkl_completeness.py
hikari/scripts/hkl_potency.py
hikari/scripts/r1_map.py
hikari/symmetry/__init__.py
hikari/symmetry/catalog.py
hikari/symmetry/group.py
hikari/symmetry/hall.py
hikari/symmetry/operations.py
hikari/utility/__init__.py
hikari/utility/artists.py
hikari/utility/certain_float.py
hikari/utility/chem_tools.py
hikari/utility/dict_tools.py
hikari/utility/interval.py
hikari/utility/list_tools.py
hikari/utility/math_tools.py
hikari/utility/numpy_tools.py
hikari/utility/os_tools.py
hikari/utility/palettes.py
hikari/utility/singleton.py
hikari/utility/typing.py
hikari_toolkit-0.3.2.dist-info/LICENSE.txt
hikari_toolkit-0.3.2.dist-info/METADATA
hikari_toolkit-0.3.2.dist-info/WHEEL
hikari_toolkit-0.3.2.dist-info/RECORD
