Metadata-Version: 2.3
Name: hikari-toolkit
Version: 0.3.2
Summary: A high-level tool for manipulating crystallographic files
License: MIT
Author: Daniel Tchoń
Author-email: dtchon@chem.uw.edu.pl
Requires-Python: >=3.9
Classifier: Development Status :: 3 - Alpha
Classifier: Environment :: Console
Classifier: Intended Audience :: Science/Research
Classifier: License :: OSI Approved :: MIT License
Classifier: Natural Language :: English
Classifier: Operating System :: OS Independent
Classifier: Programming Language :: Python
Classifier: Programming Language :: Python :: 3
Classifier: Programming Language :: Python :: 3.9
Classifier: Programming Language :: Python :: 3.10
Classifier: Programming Language :: Python :: 3.11
Classifier: Programming Language :: Python :: 3.12
Classifier: Programming Language :: Python :: 3.13
Classifier: Programming Language :: Python :: 3 :: Only
Classifier: Topic :: Scientific/Engineering
Classifier: Topic :: Scientific/Engineering :: Chemistry
Classifier: Topic :: Scientific/Engineering :: Physics
Requires-Dist: matplotlib (>=3.0.0,!=3.3.*)
Requires-Dist: numpy (>=1.25)
Requires-Dist: pandas (>=1.0.1,!=1.5.0)
Requires-Dist: scipy (>=1.5.1)
Requires-Dist: seaborn (>=0.11.0)
Requires-Dist: uncertainties (>=3)
